batabyal/__init__.py
batabyal/cleaning_module.py
batabyal/trainer_kit.py
batabyal-0.2.0.dist-info/licenses/LICENSE
batabyal-0.2.0.dist-info/METADATA
batabyal-0.2.0.dist-info/WHEEL
batabyal-0.2.0.dist-info/top_level.txt
batabyal-0.2.0.dist-info/RECORD
