Metadata-Version: 2.4
Name: batabyal
Version: 0.2.0
Summary: Data cleaning and automated ML model selection package
Author: T Batabyal
Author-email: T Batabyal <tamanashbatabyal@gmail.com>
License: MIT
Keywords: ML,DataScience
Classifier: Development Status :: 5 - Production/Stable
Classifier: Programming Language :: Python :: 3
Classifier: License :: OSI Approved :: MIT License
Classifier: Operating System :: OS Independent
Requires-Python: >=3.10
License-File: LICENSE
Requires-Dist: numpy>=1.20.0
Requires-Dist: pandas>=1.0.0
Requires-Dist: scikit-learn>=1.0.0
Dynamic: author
Dynamic: license-file
Dynamic: requires-python
